pysecsan/__init__.py
pysecsan/command_injection.py
pysecsan/redos.py
pysecsan/sanlib.py
pysecsan/yaml_deserialization.py
pysecsan-0.1.0.dist-info/LICENSE
pysecsan-0.1.0.dist-info/METADATA
pysecsan-0.1.0.dist-info/WHEEL
pysecsan-0.1.0.dist-info/top_level.txt
pysecsan-0.1.0.dist-info/RECORD
