Metadata-Version: 2.1
Name: pysecsan
Version: 0.1.0
Summary: Sanitizers to detect security vulnerabilities at runtime.
Author: David Korczynski
Author-email: David Korczynski <david@adalogics.com>
Project-URL: Homepage, https://github.com/google/oss-fuzz/tree/master/infra/sanitizers/pysecsan
Project-URL: Bug Tracker, https://github.com/google/oss-fuzz/issues
Classifier: Programming Language :: Python :: 3
Classifier: License :: OSI Approved :: Apache Software License
Classifier: Operating System :: OS Independent
Requires-Python: >=3.7
License-File: LICENSE
